calculadora_simples/Class_Calculadora.py
calculadora_simples/Executa_Calculadora.py
calculadora_simples/__init__.py
calculadora_simples-0.0.1.dist-info/METADATA
calculadora_simples-0.0.1.dist-info/WHEEL
calculadora_simples-0.0.1.dist-info/top_level.txt
calculadora_simples-0.0.1.dist-info/RECORD
