Metadata-Version: 2.1
Name: calculadora-simples
Version: 0.0.1
Summary: Calculadora com operadores simples
Home-page: https://github.com/Iaguitchu/pacote_calculadora
Author: Iago de Andrade
Author-email: iago2005andrade@gmail.com
License: UNKNOWN
Platform: UNKNOWN
Requires-Python: >=3.8
